README.md
setup.py
pylates/__init__.py
pylates/multipylates.py
pylates/pylates.py
pylates.egg-info/PKG-INFO
pylates.egg-info/SOURCES.txt
pylates.egg-info/dependency_links.txt
pylates.egg-info/top_level.txt