Metadata-Version: 2.1
Name: pylates
Version: 0.1.0
Summary: Dilation Functions in python
Home-page: https://github.com/aresio/pylates
Author: Marco S. Nobile
Author-email: marco.nobile@unimib.it
License: UNKNOWN
Platform: UNKNOWN
Classifier: Programming Language :: Python :: 3
Classifier: License :: OSI Approved :: MIT License
Classifier: Operating System :: OS Independent
